glycosylator/__init__.py
glycosylator/core/Glycan.py
glycosylator/core/__init__.py
glycosylator/core/glyco_shield.py
glycosylator/core/membrane_scaffold.py
glycosylator/core/protein_scaffold.py
glycosylator/core/scaffold.py
glycosylator/optimizers/__init__.py
glycosylator/optimizers/scaffold_rotatron.py
glycosylator/optimizers/utils.py
glycosylator/resources/__init__.py
glycosylator/resources/charmm.py
glycosylator/resources/compounds.pkl
glycosylator/resources/compounds.xml
glycosylator/resources/defaults.py
glycosylator/resources/glycosmos.py
glycosylator/resources/pdbe_compounds.py
glycosylator/resources/sequons.json
glycosylator/resources/sequons.py
glycosylator/resources/topology.xml
glycosylator/resources/icons/4eLeg.png
glycosylator/resources/icons/6dAlt.png
glycosylator/resources/icons/6dAltNAc.png
glycosylator/resources/icons/6dGul.png
glycosylator/resources/icons/6dTal.png
glycosylator/resources/icons/6dTalNAc.png
glycosylator/resources/icons/Abe.png
glycosylator/resources/icons/Aci.png
glycosylator/resources/icons/All.png
glycosylator/resources/icons/AllA.png
glycosylator/resources/icons/AllN.png
glycosylator/resources/icons/AllNAc.png
glycosylator/resources/icons/Alt.png
glycosylator/resources/icons/AltA.png
glycosylator/resources/icons/AltN.png
glycosylator/resources/icons/AltNAc.png
glycosylator/resources/icons/Api.png
glycosylator/resources/icons/Ara.png
glycosylator/resources/icons/Bac.png
glycosylator/resources/icons/Col.png
glycosylator/resources/icons/DDmanHep.png
glycosylator/resources/icons/Dha.png
glycosylator/resources/icons/Dig.png
glycosylator/resources/icons/Fru.png
glycosylator/resources/icons/Fuc.png
glycosylator/resources/icons/FucNAc.png
glycosylator/resources/icons/GLC.png
glycosylator/resources/icons/Gal.png
glycosylator/resources/icons/GalA.png
glycosylator/resources/icons/GalN.png
glycosylator/resources/icons/GalNAc.png
glycosylator/resources/icons/GlcA.png
glycosylator/resources/icons/GlcN.png
glycosylator-5.6.3.dist-info/LICENSE
glycosylator-5.6.3.dist-info/METADATA
glycosylator-5.6.3.dist-info/WHEEL
glycosylator-5.6.3.dist-info/top_level.txt
glycosylator-5.6.3.dist-info/RECORD
