Metadata-Version: 2.1
Name: glycosylator
Version: 5.6.3
Summary: A Python framework for the rapid modeling of glycans
Home-page: https://github.com/ibmm-unibe-ch/glycosylator/
Author: Noah H. Kleinschmidt
Author-email: noah.kleinschmidt@students.unibe.ch
Classifier: Programming Language :: Python :: 3
Classifier: License :: OSI Approved :: GNU General Public License v3 (GPLv3)
Classifier: Operating System :: OS Independent
Classifier: Topic :: Scientific/Engineering :: Bio-Informatics
Requires-Python: >=3.10
License-File: LICENSE
Requires-Dist: buildamol >=1.2.5
Requires-Dist: numpy
Requires-Dist: pandas
Requires-Dist: scipy
Requires-Dist: matplotlib
Requires-Dist: seaborn
Requires-Dist: networkx
Requires-Dist: biopython
Requires-Dist: pdbecif
Requires-Dist: periodictable
Requires-Dist: plotly
Requires-Dist: alive-progress
Requires-Dist: gym
Requires-Dist: pubchempy
Requires-Dist: tabulate
Requires-Dist: scikit-learn
Requires-Dist: ipywidgets <8.0.1
